{
    "0": {
        "first" : {
            "low":[110,150,20],
            "high":[130,255,255],
            "name": "blue"
            },
        "second" : {
            "low": [80,135,61],
            "high": [130,255,255],
            "name":"bible bleu"
            },
        "target" : {
            "low": [110,150,90],
            "high": [130,255,255],
            "name": "labello"
            }
    },

    "1": {
        "first" : {
            "low":[110,150,20],
            "high":[130,255,255],
            "name": "blue"
            },
        "second" : {
            "low":[0,151,114],
            "high":[10,227,255],
            "name":"red"
            },
        "target" : {
            "low": [110,150,90],
            "high": [130,255,255],
            "name": "labello"
            }
    }
}